observicia/__init__.py
observicia/core/__init__.py
observicia/core/context_manager.py
observicia/core/patch_manager.py
observicia/core/policy_engine.py
observicia/core/token_tracker.py
observicia/core/tracing_manager.py
observicia/patchers/__init__.py
observicia/patchers/anthropic.py
observicia/patchers/litellm.py
observicia/patchers/ollama.py
observicia/patchers/openai.py
observicia/patchers/watsonx.py
observicia/utils/__init__.py
observicia/utils/exporter.py
observicia/utils/helpers.py
observicia/utils/logging.py
observicia/utils/policy_helpers.py
observicia/utils/serialization_helpers.py
observicia/utils/stream_helpers.py
observicia/utils/token_helpers.py
observicia/utils/tracing_helpers.py
tests/__init__.py
tests/test_context_manager.py
tests/test_ollama_patcher.py
tests/test_openai_patcher.py
tests/test_patch_manager.py
tests/test_token_tracker.py
tests/test_utils_functions.py
observicia-0.1.13.dist-info/LICENSE
observicia-0.1.13.dist-info/METADATA
observicia-0.1.13.dist-info/WHEEL
observicia-0.1.13.dist-info/top_level.txt
observicia-0.1.13.dist-info/RECORD
