Metadata-Version: 2.1
Name: observicia
Version: 0.1.13
Summary: Cloud Native Observability SDK for LLM applications
Home-page: https://github.com/observicia/observicia
Project-URL: Documentation, https://observicia.readthedocs.io/
Project-URL: Bug Reports, https://github.com/observicia/observicia/issues
Project-URL: Source, https://github.com/observicia/observicia
Project-URL: Discussion, https://github.com/observicia/observicia/discussions
Keywords: llm,observability,monitoring,tracing,opentelemetry,opa
Platform: any
Classifier: Development Status :: 4 - Beta
Classifier: Intended Audience :: Developers
Classifier: License :: OSI Approved :: Apache Software License
Classifier: Operating System :: OS Independent
Classifier: Programming Language :: Python :: 3
Classifier: Programming Language :: Python :: 3.8
Classifier: Programming Language :: Python :: 3.9
Classifier: Programming Language :: Python :: 3.10
Classifier: Programming Language :: Python :: 3.11
Classifier: Topic :: Software Development :: Libraries :: Python Modules
Classifier: Topic :: System :: Monitoring
Classifier: Topic :: Scientific/Engineering :: Artificial Intelligence
Requires-Python: >=3.8
License-File: LICENSE
Requires-Dist: numpy>=1.26.0
Requires-Dist: requests>=2.32.3
Requires-Dist: tiktoken>=0.7.0
Requires-Dist: opentelemetry-api>=1.22.0
Requires-Dist: opentelemetry-sdk>=1.22.0
Requires-Dist: opentelemetry-exporter-otlp>=1.22.0
Requires-Dist: opentelemetry-instrumentation>=0.43b0
Requires-Dist: openai>=1.55.3
Requires-Dist: pyyaml>=6.0
Requires-Dist: redis>=5.2.0
Requires-Dist: ollama>=0.4.4
Requires-Dist: ibm_watsonx_ai>=1.1.26
